spatial_lda/__init__.py
spatial_lda/admm.py
spatial_lda/featurization.py
spatial_lda/model.py
spatial_lda/online_lda.py
spatial_lda/primal_dual.py
spatial_lda/visualization.py
tests/__init__.py
tests/test_admm.py
tests/test_featurization.py
spatial_lda-0.1.3.dist-info/LICENSE
spatial_lda-0.1.3.dist-info/METADATA
spatial_lda-0.1.3.dist-info/WHEEL
spatial_lda-0.1.3.dist-info/top_level.txt
spatial_lda-0.1.3.dist-info/RECORD
