Metadata-Version: 2.1
Name: spatial-lda
Version: 0.1.3
Summary: Implementation of the Spatial-LDA model
Home-page: https://github.com/calico/spatial_lda/
Author: Zhenghao Chen, Vladimir Jojic
Author-email: zhenghao@calicolabs.com, vjojic@calicolabs.com
License: UNKNOWN
Platform: UNKNOWN
Classifier: Programming Language :: Python :: 3
Classifier: License :: OSI Approved :: MIT License
Classifier: Operating System :: OS Independent
Requires-Python: >=3.6
